thecampy/__init__.py
thecampy/client.py
thecampy/exceptions.py
thecampy/image_utils.py
thecampy/images.py
thecampy/models.py
thecampy/utils.py
thecampy-3.0.2.dist-info/LICENSE
thecampy-3.0.2.dist-info/METADATA
thecampy-3.0.2.dist-info/WHEEL
thecampy-3.0.2.dist-info/top_level.txt
thecampy-3.0.2.dist-info/RECORD
