Metadata-Version: 2.1
Name: thecampy
Version: 3.0.2
Summary: 더 캠프 인터넷편지 비공식 라이브러리
Home-page: https://github.com/lewisleedev/thecampy
Author: lewisleedev
Author-email: lewislee@lewislee.net
License: UNKNOWN
Platform: UNKNOWN
Classifier: Programming Language :: Python :: 3
Classifier: License :: OSI Approved :: MIT License
Classifier: Operating System :: OS Independent
Requires-Python: >=3.6
Requires-Dist: requests
